{
  "id": "c1e1dded-fe3d-4b1f-905e-22d41f11bc3c",
  "prevId": "00000000-0000-0000-0000-000000000000",
  "version": "7",
  "dialect": "postgresql",
  "tables": {
    "public.admin_roles": {
      "name": "admin_roles",
      "schema": "",
      "columns": {
        "id": {
          "name": "id",
          "type": "serial",
          "primaryKey": true,
          "notNull": true
        },
        "admin_id": {
          "name": "admin_id",
          "type": "integer",
          "primaryKey": false,
          "notNull": true
        },
        "role_id": {
          "name": "role_id",
          "type": "integer",
          "primaryKey": false,
          "notNull": true
        },
        "created_at": {
          "name": "created_at",
          "type": "timestamp with time zone",
          "primaryKey": false,
          "notNull": true,
          "default": "now()"
        }
      },
      "indexes": {
        "admin_roles_admin_id_role_id_unique": {
          "name": "admin_roles_admin_id_role_id_unique",
          "columns": [
            {
              "expression": "admin_id",
              "isExpression": false,
              "asc": true,
              "nulls": "last"
            },
            {
              "expression": "role_id",
              "isExpression": false,
              "asc": true,
              "nulls": "last"
            }
          ],
          "isUnique": true,
          "concurrently": false,
          "method": "btree",
          "with": {}
        }
      },
      "foreignKeys": {
        "admin_roles_admin_id_admins_id_fk": {
          "name": "admin_roles_admin_id_admins_id_fk",
          "tableFrom": "admin_roles",
          "tableTo": "admins",
          "columnsFrom": [
            "admin_id"
          ],
          "columnsTo": [
            "id"
          ],
          "onDelete": "cascade",
          "onUpdate": "no action"
        },
        "admin_roles_role_id_roles_id_fk": {
          "name": "admin_roles_role_id_roles_id_fk",
          "tableFrom": "admin_roles",
          "tableTo": "roles",
          "columnsFrom": [
            "role_id"
          ],
          "columnsTo": [
            "id"
          ],
          "onDelete": "cascade",
          "onUpdate": "no action"
        }
      },
      "compositePrimaryKeys": {},
      "uniqueConstraints": {},
      "policies": {},
      "checkConstraints": {},
      "isRLSEnabled": false
    },
    "public.admins": {
      "name": "admins",
      "schema": "",
      "columns": {
        "id": {
          "name": "id",
          "type": "serial",
          "primaryKey": true,
          "notNull": true
        },
        "username": {
          "name": "username",
          "type": "text",
          "primaryKey": false,
          "notNull": true
        },
        "password": {
          "name": "password",
          "type": "text",
          "primaryKey": false,
          "notNull": true
        },
        "nickname": {
          "name": "nickname",
          "type": "text",
          "primaryKey": false,
          "notNull": true
        },
        "status": {
          "name": "status",
          "type": "account_status",
          "typeSchema": "public",
          "primaryKey": false,
          "notNull": true,
          "default": "'active'"
        },
        "created_at": {
          "name": "created_at",
          "type": "timestamp with time zone",
          "primaryKey": false,
          "notNull": true,
          "default": "now()"
        },
        "updated_at": {
          "name": "updated_at",
          "type": "timestamp with time zone",
          "primaryKey": false,
          "notNull": true,
          "default": "now()"
        }
      },
      "indexes": {
        "admins_username_unique": {
          "name": "admins_username_unique",
          "columns": [
            {
              "expression": "username",
              "isExpression": false,
              "asc": true,
              "nulls": "last"
            }
          ],
          "isUnique": true,
          "concurrently": false,
          "method": "btree",
          "with": {}
        }
      },
      "foreignKeys": {},
      "compositePrimaryKeys": {},
      "uniqueConstraints": {},
      "policies": {},
      "checkConstraints": {},
      "isRLSEnabled": false
    },
    "public.roles": {
      "name": "roles",
      "schema": "",
      "columns": {
        "id": {
          "name": "id",
          "type": "serial",
          "primaryKey": true,
          "notNull": true
        },
        "code": {
          "name": "code",
          "type": "text",
          "primaryKey": false,
          "notNull": true
        },
        "name": {
          "name": "name",
          "type": "text",
          "primaryKey": false,
          "notNull": true
        },
        "created_at": {
          "name": "created_at",
          "type": "timestamp with time zone",
          "primaryKey": false,
          "notNull": true,
          "default": "now()"
        },
        "updated_at": {
          "name": "updated_at",
          "type": "timestamp with time zone",
          "primaryKey": false,
          "notNull": true,
          "default": "now()"
        }
      },
      "indexes": {
        "roles_code_unique": {
          "name": "roles_code_unique",
          "columns": [
            {
              "expression": "code",
              "isExpression": false,
              "asc": true,
              "nulls": "last"
            }
          ],
          "isUnique": true,
          "concurrently": false,
          "method": "btree",
          "with": {}
        }
      },
      "foreignKeys": {},
      "compositePrimaryKeys": {},
      "uniqueConstraints": {},
      "policies": {},
      "checkConstraints": {},
      "isRLSEnabled": false
    },
    "public.users": {
      "name": "users",
      "schema": "",
      "columns": {
        "id": {
          "name": "id",
          "type": "serial",
          "primaryKey": true,
          "notNull": true
        },
        "username": {
          "name": "username",
          "type": "text",
          "primaryKey": false,
          "notNull": true
        },
        "password": {
          "name": "password",
          "type": "text",
          "primaryKey": false,
          "notNull": true
        },
        "nickname": {
          "name": "nickname",
          "type": "text",
          "primaryKey": false,
          "notNull": true
        },
        "status": {
          "name": "status",
          "type": "account_status",
          "typeSchema": "public",
          "primaryKey": false,
          "notNull": true,
          "default": "'active'"
        },
        "created_at": {
          "name": "created_at",
          "type": "timestamp with time zone",
          "primaryKey": false,
          "notNull": true,
          "default": "now()"
        },
        "updated_at": {
          "name": "updated_at",
          "type": "timestamp with time zone",
          "primaryKey": false,
          "notNull": true,
          "default": "now()"
        }
      },
      "indexes": {
        "users_username_unique": {
          "name": "users_username_unique",
          "columns": [
            {
              "expression": "username",
              "isExpression": false,
              "asc": true,
              "nulls": "last"
            }
          ],
          "isUnique": true,
          "concurrently": false,
          "method": "btree",
          "with": {}
        }
      },
      "foreignKeys": {},
      "compositePrimaryKeys": {},
      "uniqueConstraints": {},
      "policies": {},
      "checkConstraints": {},
      "isRLSEnabled": false
    }
  },
  "enums": {
    "public.account_status": {
      "name": "account_status",
      "schema": "public",
      "values": [
        "active",
        "disabled"
      ]
    }
  },
  "schemas": {},
  "sequences": {},
  "roles": {},
  "policies": {},
  "views": {},
  "_meta": {
    "columns": {},
    "schemas": {},
    "tables": {}
  }
}